elite_relay/__init__.py
elite_relay/journal.py
elite_relay/main.py
elite_relay/settings.py
elite_relay/plugins/__init__.py
elite_relay/plugins/base.py
elite_relay/plugins/registry.py
elite_relay/plugins/browser/__init__.py
elite_relay/plugins/browser/plugin.py
elite_relay/plugins/clipboard/__init__.py
elite_relay/plugins/clipboard/plugin.py
elite_relay/plugins/http/__init__.py
elite_relay/plugins/http/plugin.py
elite_relay/plugins/pushover/__init__.py
elite_relay/plugins/pushover/plugin.py
elite_relay-0.2.1.dist-info/licenses/LICENSE
elite_relay-0.2.1.dist-info/METADATA
elite_relay-0.2.1.dist-info/WHEEL
elite_relay-0.2.1.dist-info/entry_points.txt
elite_relay-0.2.1.dist-info/top_level.txt
elite_relay-0.2.1.dist-info/RECORD
