Metadata-Version: 2.4
Name: elite-relay
Version: 0.2.1
Summary: Elite: Dangerous Journal Event Handler
Requires-Python: >=3.11
License-File: LICENSE
Requires-Dist: jmespath>=1.0.1
Requires-Dist: orjson>=3.11.4
Requires-Dist: pydantic>=2.12.4
Requires-Dist: pydantic-settings[yaml]>=2.11.0
Requires-Dist: pyperclip>=1.11.0
Requires-Dist: requests>=2.32.5
Dynamic: license-file
